mazurka/__init__.py
mazurka/__main__.py
mazurka/assets/gpt2.tiktoken
mazurka/assets/mel_filters.npz
mazurka/assets/multilingual.tiktoken
mazurka/audio.py
mazurka/decoding.py
mazurka/model.py
mazurka/normalizers/__init__.py
mazurka/normalizers/basic.py
mazurka/normalizers/english.json
mazurka/normalizers/english.py
mazurka/timing.py
mazurka/tokenizer.py
mazurka/transcribe.py
mazurka/triton_ops.py
mazurka/utils.py
mazurka-2024rc1.dist-info/METADATA
mazurka-2024rc1.dist-info/WHEEL
mazurka-2024rc1.dist-info/entry_points.txt
mazurka-2024rc1.dist-info/RECORD
