Metadata-Version: 2.1
Name: mazurka
Version: 2024rc1
Summary: 
Author: fineartit
Author-email: fineartit@outlook.com
Requires-Python: >=3.11,<4.0
Classifier: Programming Language :: Python :: 3
Classifier: Programming Language :: Python :: 3.11
Classifier: Programming Language :: Python :: 3.12
Requires-Dist: more-itertools (>=10.3.0,<11.0.0)
Requires-Dist: numba (>=0.60.0,<0.61.0)
Requires-Dist: numpy (>=1.26.4,<2.0.0)
Requires-Dist: tiktoken (>=0.7.0,<0.8.0)
Requires-Dist: torch (>=2.3.1,<3.0.0)
Requires-Dist: tqdm (>=4.66.4,<5.0.0)
